<?xml version="1.0" encoding="utf-8"?>
<message_catalog package_key="intranet-invoices" locale="pl_PL" charset="utf-8">

  <msg key="Add_a_Payment">Dodaj płatność</msg>
  <msg key="Add_a_Project">Dodaj projekt</msg>
  <msg key="Add_a_user">Dodaj użytkownika</msg>
  <msg key="Add_Payment">Dodaj płatność</msg>
  <msg key="Admin_Links">Linki administratora</msg>
  <msg key="Adress">Adres</msg>
  <msg key="Amount">Ilość</msg>
  <msg key="Associate_cost_type_with_project">Powiąż typ kosztu z projektem</msg>
  <msg key="Blurb_multiple_currencies">Wykorzystałeś więcej niż jedną walutę w tym dokumencie finansowym. Nie jest to obsługiwane przez tę wersję ]project-open[. Podziel dokument na kilka dokumentów, każdy z jedną walutą. Wykorzystałeś następujące waluty:</msg>
  <msg key="CC">CK</msg>
  <msg key="Client">Klient</msg>
  <msg key="Clone">Klonuj</msg>
  <msg key="clone">Klonuj</msg>
  <msg key="Company">Firma</msg>
  <msg key="Company_1">Firma:</msg>
  <msg key="Company_name">Nazwa firmy</msg>
  <msg key="company_name_page">Strona %company_name%</msg>
  <msg key="Contact">Kontakt</msg>
  <msg key="Cost">Koszt</msg>
  <msg key="Cost_Center">Centrum kosztów</msg>
  <msg key="cost_type_Data">%cost_type% - Dane</msg>
  <msg key="cost_type_date">%cost_type% - data</msg>
  <msg key="cost_type_due_date">%cost_type% - due date:</msg>
  <msg key="cost_type_nr">%cost_type% - nr</msg>
  <msg key="cost_type_status">%cost_type% - status</msg>
  <msg key="cost_type_template">%cost_type% - szablon:</msg>
  <msg key="cost_type_type">Typ %cost_type%</msg>
  <msg key="cost_type_type_1">%cost_type% - typ:</msg>
  <msg key="Costs">Koszty</msg>
  <msg key="Country">Kraj</msg>
  <msg key="Customer">Klient</msg>
  <msg key="Customer_Documents">Dokumenty finansowe klientów</msg>
  <msg key="Customer_Invoice">Faktura sprzedażowa</msg>
  <msg key="Customers">Klienci</msg>
  <msg key="Date">Data</msg>
  <msg key="days">dni</msg>
  <msg key="Del">Usuń</msg>
  <msg key="Delete">Usuń</msg>
  <msg key="Description">Opis</msg>
  <msg key="Document_">Dokument #</msg>
  <msg key="Document_hash_simbol">Dokument #</msg>
  <msg key="Document_No">Nr dokumentu</msg>
  <msg key="Document_Status">Status dokumentu:</msg>
  <msg key="Document_Type">Rodzaj dokumentu:</msg>
  <msg key="Due_Date">Termin</msg>
  <msg key="Duplicate_Invoice">Powiel fakturę</msg>
  <msg key="Edit">Edytuj</msg>
  <msg key="Edit_cost_type">Zapisz %cost_type%</msg>
  <msg key="Edit_cost_type_1">Edytuj %cost_type</msg>
  <msg key="Effective_Date">Data wymagalności</msg>
  <msg key="Email">E-mail</msg>
  <msg key="Error_Document_Nr_exists">Dokument nr nie będzie już dostępny, zanotuj i zweryfikuj nowonadany numer</msg>
  <msg key="Error_multiple_currencies">Błąd wielu walut</msg>
  <msg key="Export_Companies_CSV">Eksportuj firmy do CSV</msg>
  <msg key="Export_Company_Cube">Eksportuj kostkę firm</msg>
  <msg key="Export_Customer_Invoice_Cube">Eksportuj kostkę faktur sprzedaży</msg>
  <msg key="Export_Customer_Invoices_CSV">Eksport faktur sprzedażowych do CSV</msg>
  <msg key="Export_Invoices_CSV">Eksportuj faktury do CSV</msg>
  <msg key="Export_Project_Cube">Eksportuj kostkę z projektami</msg>
  <msg key="Export_Projects_CSV">Eksportuj projekty do CSV</msg>
  <msg key="Export_Provider_Invoice_Cube">Eksportuj kostkę z fakturami dostawców</msg>
  <msg key="Export_Provider_Invoices_CSV">Wyeksportuj faktury dostawców do CSV</msg>
  <msg key="Fax">Fax</msg>
  <msg key="Filter_Documents">Filtruj dokumenty</msg>
  <msg key="Finance">Finanse</msg>
  <msg key="Finance_List">Lista finansów</msg>
  <msg key="Financial_Documents">Dokumenty finansowe</msg>
  <msg key="From">Od:</msg>
  <msg key="General_Manager">Dyrektor generalny</msg>
  <msg key="Generate_Delivery_Note_from_Quote">Nowy protokół odbioru z wyceny</msg>
  <msg key="Generate_Invoice_from_Quote">Nowa faktura z wyceny</msg>
  <msg key="Generate_Provider_Bill_from_Purchase_Order">Utwórz rachunek dostawcy z zamówienia</msg>
  <msg key="Go">Idź</msg>
  <msg key="Hour">Godzina</msg>
  <msg key="InterCo_Quote_New">Nowa wycena InterCo</msg>
  <msg key="intranet-invoices.Error_multiple_currencies">Błąd wielu walut</msg>
  <msg key="Invoice_Address">Adres faktury</msg>
  <msg key="Line">Linia</msg>
  <msg key="lt_Cant_find_the_documen">Nie mogę znaleźć dokumentu #%invoice_id%</msg>
  <msg key="lt_Dear_accounting_conta">Drogi %accounting_contact_name%, Nowy %cost_type% został utworzony dla Ciebie: %system_url%/intranet-invoices/view?invoice_id=%invoice_id% Wejdź proszę na powyższy link i wydrukuj dokument. Nowy dokument jest przyporządkowany do projektu: %select_projects;noquote% Jeżeli masz jakiekolwiek pytania skontaktuj się ze mną przez e-mail. Pozdrawiam %current_user_name%</msg>
  <msg key="lt_Generate_Invoice_from">Utwórz fakturę z wyceny</msg>
  <msg key="lt_Generate_Provider_Bil">Utwórz rachunek dostawcy z zamówienia</msg>
  <msg key="lt_Insufficient_Privileg">Niewystarczające uprawnienia</msg>
  <msg key="lt_New_Company_Documents">Nowe dokumenty</msg>
  <msg key="lt_No_Accounting_Contact">Nie zdefiniowano kontaktu do księgowości</msg>
  <msg key="lt_payment_days_days_dat">%payment_days% dni od daty wystawienia faktury</msg>
  <msg key="lt_Please_contact_your_s">Skontaktuj się z twoim administratorem systemu jeżeli uważasz, że to błąd.</msg>
  <msg key="lt_Please_visit_the_link">Wejdź na %link_to_page% i dodaj kontakt do księgowości.</msg>
  <msg key="lt_Send_as_email_to_prov">Wyślij jako e-mail do %provider_company%</msg>
  <msg key="lt_Send_cost_type_via_Em">Wyśli %cost_type% jako e-mail</msg>
  <msg key="lt_system_name_New_cost_">%system_name%: Nowy %cost_type%</msg>
  <msg key="lt_The_company_company_n">Firma %company_name% nie ma zdefiniowanego kontaktu do księgowości, do którego można by wysłać ten %cost_type%.</msg>
  <msg key="lt_There_are_currently_n">Obecnie nie ma żadnych faktur spełniających zadane kryteria</msg>
  <msg key="lt_This_invoice_is_past_">Ta faktura ma termin płatności %calculated_due_date_pretty%.</msg>
  <msg key="lt_You_dont_have_suffici">Nie masz wystarczających uprawnień, żeby oglądać tę stronę.</msg>
  <msg key="lt_You_have_insufficient">Masz niewystarczające uprawnienia, żeby oglądać tę stronę.</msg>
  <msg key="lt_You_have_insufficient_1">Masz niewystarczające uprawnienia, żeby oglądać tę stronę.</msg>
  <msg key="lt_You_need_to_specify_a">Musisz podać invoice_id</msg>
  <msg key="New_Bank_Holiday">Nowe święto państwowe</msg>
  <msg key="New_Company_Invoice_from_Quote">Nowa faktura z wyceny</msg>
  <msg key="New_Company_Invoice_from_scratch">Nowa faktura od zera</msg>
  <msg key="New_cost_type">Nowa %cost_type%</msg>
  <msg key="New_Customer_Invoice_from_Delivery_Note">Nowa faktura sprzedażowa na podstawie protokołu odbioru</msg>
  <msg key="New_Customer_Invoice_from_Invoice">Nowa faktura sprzedażowa na podstawie faktury</msg>
  <msg key="New_Customer_Invoice_from_Quote">Nowa faktura sprzedażowa na podstawie wyceny</msg>
  <msg key="New_Customer_Invoice_from_scratch">Nowa faktura sprzedażowa</msg>
  <msg key="New_Customer_Invoice_from_Timesheet_Tasks">Nowa faktura sprzedażowa na podstawie harmonogramu zadań</msg>
  <msg key="New_Customer_Invoice_from_Translation_Tasks">Nowa faktura sprzedażowa z zadań tłumaczenia</msg>
  <msg key="New_Delivery_Note_from_Quote">Nowy protokół odbioru na podstawie wyceny</msg>
  <msg key="New_Delivery_Note_from_scratch">Nowy protokół odbioru</msg>
  <msg key="New_Delivery_Note_from_Translation_Tasks">Nowy protokół odbioru z tasków tłumaczenia</msg>
  <msg key="New_InterCo_Invoice_from_Translation_Tasks">Nowa faktura InterCo z tasków tłumaczenia</msg>
  <msg key="New_InterCo_Quote_from_Translation_Tasks">Nowa wycena InterCo z tasków tłumaczenia</msg>
  <msg key="New_Personal_Absence">Nowa nieobecność</msg>
  <msg key="New_Provider_Bill_from_Purchase_Order">Nowy dokument dostawcy na podstawie zamówienia</msg>
  <msg key="New_Provider_Bill_from_scratch">Nowy rachunek dostawcy</msg>
  <msg key="New_Provider_Bill_from_Translation_Tasks">Nowy rachunek dostawcy w tasków tłumaczenia</msg>
  <msg key="New_Provider_Invoice_from_Translation_Tasks">Nowy faktura dostawcy w tasków tłumaczenia</msg>
  <msg key="New_Purchase_Order_from_scratch">Nowe zamówienie od zera</msg>
  <msg key="New_Purchase_Order_from_Translation_Tasks">Nowe zamówienie z tasków tłumaczenia</msg>
  <msg key="New_Quote_from_Quote">Nowa wycena na podstawie wyceny</msg>
  <msg key="New_Quote_from_scratch">Nowa wycena</msg>
  <msg key="New_Quote_from_Timesheet_Tasks">Nowa wycena na podstawie harmonogramu zadań</msg>
  <msg key="New_Quote_from_Translation_Tasks">Nowa wycena z tasków tłumaczenia</msg>
  <msg key="New_Sick_Leave">Nowe zwolnienie lekarskie</msg>
  <msg key="New_Translation_Customer_Invoice">Nowa faktura sprzedażowa za tłumaczenie</msg>
  <msg key="New_Translation_Invoice">Nowa faktura za tłumaczenie</msg>
  <msg key="New_Translation_Provider_Invoice">Nowa faktura dostawcy za tłumaczenie</msg>
  <msg key="New_Translation_Purchase_Order">Nowe zamówienie na tłumaczenie</msg>
  <msg key="New_Translation_Quote">Nowa wycena tłumaczenia</msg>
  <msg key="New_Travel_Absence">Nowa podróż</msg>
  <msg key="New_Vacation_Absence">Nowy urlop</msg>
  <msg key="Next_Page">Następna strona</msg>
  <msg key="No_command_specified">Nie podano komendy</msg>
  <msg key="No_objects_found">Nie znaleziono żadnych obiektów</msg>
  <msg key="No_payments_found">Nie znaleziono płatności</msg>
  <msg key="No_Template_Defined">Nie zdefiniowałeś wzorca dla faktury, wyceny lub zamówienia. Wróć i wybierz odpowiedni wzorzec.</msg>
  <msg key="Note">Uwagi:</msg>
  <msg key="Notify_user">Powiadom użytkownika</msg>
  <msg key="One_cost_type">Jeden %cost_type%</msg>
  <msg key="Our_Ref">Nasz nr ref.</msg>
  <msg key="Paid">Płatność</msg>
  <msg key="Payment_date">Data płatności</msg>
  <msg key="Payment_Method">Metoda płatności</msg>
  <msg key="Payment_Method_1">Metoda płatności:</msg>
  <msg key="Payment_Terms">Warunki płatności:</msg>
  <msg key="Payment_terms">Warunki płatności</msg>
  <msg key="Payment_Type">Typ płatności</msg>
  <msg key="Phone">Telefon</msg>
  <msg key="Preview">Podejrzyj</msg>
  <msg key="Preview_as_HTML">Podejrzyj jako HTML</msg>
  <msg key="Preview_as_PDF">Podejrzyj jako PDF</msg>
  <msg key="Preview_using_template">Podejrzyj z użyciem wzorca</msg>
  <msg key="Previous_Page">Poprzednia strona</msg>
  <msg key="Provider">Dostawca</msg>
  <msg key="Provider_1">Dostawca:</msg>
  <msg key="Provider_Bill">Rachunek dostawcy</msg>
  <msg key="Providers">Dostawcy</msg>
  <msg key="Purchase_Order">Zamówienie</msg>
  <msg key="Qty">Ilość</msg>
  <msg key="Quote">Wycena</msg>
  <msg key="Rate">Stawka</msg>
  <msg key="Recipient">Odbiorca</msg>
  <msg key="Related_Payments">Powiązane płatności</msg>
  <msg key="Related_Projects">Powiązane projekty</msg>
  <msg key="Resource_Planning_Report">Raport planowania zasobów</msg>
  <msg key="Save">Zapisz</msg>
  <msg key="Save_Changes">Zachowaj zmiany</msg>
  <msg key="Sel">Wybór</msg>
  <msg key="Select">Wybierz</msg>
  <msg key="Select_Customer">Wybierz klienta</msg>
  <msg key="Select_documents">Wybierz dokumenty</msg>
  <msg key="Select_Project">Wybierz projekt</msg>
  <msg key="Select_Provider">Wybierz dostawcę</msg>
  <msg key="Send_document_as_HTML_attachment">Wyślij dokument jako załącznik HTML</msg>
  <msg key="Send_document_as_HTML_link">Wyślij dokument jako link HTML</msg>
  <msg key="Send_document_as_PDF_attachment">Wyślij dokument jako załącznik PDF</msg>
  <msg key="Send_invoice_as_HTML_attachment">Wyślij fakturę jako załącznik HTML</msg>
  <msg key="Send_invoice_as_HTML_link">Wyślij fakturę jako link HTML</msg>
  <msg key="Send_invoice_as_link">Wyślij fakturę jako link</msg>
  <msg key="Set_to_invoiced">Dodaj do fakturowanych</msg>
  <msg key="Set_to_status_Created">Ustaw status na Utworzony</msg>
  <msg key="Set_to_status_Filed">Ustaw status na Zapisany</msg>
  <msg key="Set_to_status_Outstanding">Ustaw status na Zaległy</msg>
  <msg key="Set_to_status_Paid">Ustaw status na Zapłacony</msg>
  <msg key="Set_to_status_Partially_Paid">Ustaw status na Częściowo zapłacony</msg>
  <msg key="Set_to_status_Past_Due">Ustaw status na Po terminie</msg>
  <msg key="Set_to_status_Rejected">Ustaw status na Odrzucony</msg>
  <msg key="Set_to_status_Requested">Ustaw status na Wniosek</msg>
  <msg key="Show_Included_Timesheet_Hours">Pokaż godziny z faktury</msg>
  <msg key="Start_Confirmation_Workflow">Uruchom proces potwierdzenia</msg>
  <msg key="Status">Status</msg>
  <msg key="Submit">Zapisz</msg>
  <msg key="Subtotal">Suma częściowa</msg>
  <msg key="TAX">TAX</msg>
  <msg key="TAXnbsp">TAX&amp;nbsp;</msg>
  <msg key="The_indicated_prices_dont_include_VAT">Wskazane ceny nie zawierają VAT</msg>
  <msg key="Timesheet_Cube">Zestawienie czasu pracy</msg>
  <msg key="Timesheet_Customers_and_Projects">Czas pracy nad klientami i projektami</msg>
  <msg key="Timesheet_Productivity">Efektywność czasu pracy</msg>
  <msg key="Timesheet_Project_Hierarchy___Finance">Czas pracy - hierarchia projektu i finanse</msg>
  <msg key="Timesheet_Weekly_Report">Raport tygodniowy czasu pracy</msg>
  <msg key="Timesheet_Workflow___Unconfirmed_Hours">Przepływ pracy czasu pracy - niepotwierdzone godziny</msg>
  <msg key="To">Do:</msg>
  <msg key="Total">Suma</msg>
  <msg key="Total_Due">Do zapłaty</msg>
  <msg key="Type">Typ</msg>
  <msg key="Unit">Jedn.</msg>
  <msg key="Units">Jednostki</msg>
  <msg key="UOM">J.M.</msg>
  <msg key="Update_Financial_Documents">Uaktualnij dokumenty finansowe</msg>
  <msg key="VAT">VAT</msg>
  <msg key="VATnbsp">VAT&amp;nbsp;</msg>
  <msg key="Your_Reference">Twój nr ref. </msg>
  <msg key="Yr_Job__PO_No">Nr zamówienia</msg>
  <msg key="Zip">Kod pocztowy</msg>
</message_catalog>
